microweb/__init__.py
microweb/cli.py
microweb/dotenv.py
microweb/microweb.py
microweb/uploader.py
microweb/wifi.py
microweb/firmware/ESP32_GENERIC-20250415-v1.25.0.bin
microweb/firmware/ESP8266_GENERIC-20250415-v1.25.0.bin
microweb/firmware/boot.py
microweb/firmware/main.py
microweb-0.2.1.dist-info/licenses/LICENSE
microweb-0.2.1.dist-info/METADATA
microweb-0.2.1.dist-info/WHEEL
microweb-0.2.1.dist-info/entry_points.txt
microweb-0.2.1.dist-info/top_level.txt
microweb-0.2.1.dist-info/RECORD
