Metadata-Version: 2.4
Name: microweb
Version: 0.2.1
Summary: A lightweight web server framework for MicroPython on ESP32, supporting dynamic routing, template rendering with for loops and conditionals, and static file serving.
Home-page: https://github.com/ishanoshada/microweb
Author: Ishan Oshada
Keywords: micropython,esp32,web server,embedded,iot,http,microcontroller,python,template engine,for loops,conditionals,static files,json
Classifier: Programming Language :: Python :: 3
Classifier: License :: OSI Approved :: MIT License
Classifier: Operating System :: OS Independent
Classifier: Topic :: Software Development :: Embedded Systems
Classifier: Topic :: Internet :: WWW/HTTP :: HTTP Servers
Classifier: Topic :: Software Development :: Libraries :: Application Frameworks
License-File: LICENSE
Requires-Dist: pyserial
Requires-Dist: esptool
Requires-Dist: click
Requires-Dist: adafruit-ampy
Requires-Dist: mpremote
Dynamic: author
Dynamic: classifier
Dynamic: description
Dynamic: description-content-type
Dynamic: home-page
Dynamic: keywords
Dynamic: license-file
Dynamic: requires-dist
Dynamic: summary
